{"runner_info": {"Bib Number": "001352", "Name": "\u9ec3\u7ae3\u744b", "Event": "MA", "Group": "\u753730-39\u6b72", "Nation": "TPE", "Gender": "\u7537", "Gun Time": "04:18:03", "Net Time": "04:11:01"}, "record": {"cp": {"-1": {"CPId": "0", "CPName": "Gun Start", "CPDistance": 0, "CPField": "TimeGun", "CPAccumulate": 0, "unixTOD": 1734215400.4, "unixtime": 1734215400.4, "chip_time": 0, "time": "06:30:00", "section_total_rank": null, "sTime": "--:--:--", "cumulativeTime": "00:00:00", "raceTime": "00:00:00", "averageRate": "--:--", "sRate": "--:--"}, "0": {"CPId": "00", "CPName": "Start", "CPDistance": 0, "CPField": "TimeStart", "CPAccumulate": 0, "unixTOD": 1734215822.2, "unixtime": 1734215822.2, "chip_time": 0, "time": "06:37:02", "section_total_rank": null, "sTime": "--:--:--", "cumulativeTime": "00:00:00", "raceTime": "00:00:00", "averageRate": "--:--", "sRate": "--:--"}, "1": {"CPId": "01", "CPName": "5k", "CPDistance": 5000, "CPField": "TimeChk_05km", "CPAccumulate": 5000, "unixTOD": 1734217679.5, "unixtime": 1734217679.5, "chip_time": "1857.300", "time": "07:07:59", "section_total_rank": null, "sTime": "00:30:58", "cumulativeTime": "00:30:58", "raceTime": "00:30:58", "averageRate": "06:11", "speed": 2.69, "rate": 371, "sRate": "06:11"}, "2": {"CPId": "02", "CPName": "10k", "CPDistance": 5000, "CPField": "TimeChk_10km", "CPAccumulate": 10000, "unixTOD": 1734219541.9, "unixtime": 1734219541.9, "chip_time": "3719.700", "time": "07:39:01", "section_total_rank": null, "sTime": "00:31:03", "cumulativeTime": "01:02:00", "raceTime": "01:02:00", "averageRate": "06:11", "speed": 2.68, "rate": 372, "sRate": "06:12"}, "3": {"CPId": "03", "CPName": "15k", "CPDistance": 5000, "CPField": "TimeChk_15km", "CPAccumulate": 15000, "unixTOD": 1734221291.35, "unixtime": 1734221291.35, "chip_time": "5469.150", "time": "08:08:11", "section_total_rank": null, "sTime": "00:29:10", "cumulativeTime": "01:31:10", "raceTime": "01:31:10", "averageRate": "06:04", "speed": 2.86, "rate": 350, "sRate": "05:49"}, "4": {"CPId": "04", "CPName": "20k", "CPDistance": 5000, "CPField": "TimeChk_20km", "CPAccumulate": 20000, "unixTOD": 1734222998.5, "unixtime": 1734222998.5, "chip_time": "7176.300", "time": "08:36:38", "section_total_rank": null, "sTime": "00:28:28", "cumulativeTime": "01:59:37", "raceTime": "01:59:37", "averageRate": "05:58", "speed": 2.93, "rate": 341, "sRate": "05:41"}, "5": {"CPId": "05", "CPName": "21k", "CPDistance": 1000, "CPField": "TimeSplitM1", "CPAccumulate": 15220, "unixTOD": 1734223402.3, "unixtime": 1734223402.3, "chip_time": "7580.100", "time": "08:43:22", "section_total_rank": null, "sTime": "00:06:44", "cumulativeTime": "02:06:21", "raceTime": "02:06:21", "averageRate": "06:00", "speed": 2.48, "rate": 404, "sRate": "06:43"}, "6": {"CPId": "06", "CPName": "25k", "CPDistance": 4000, "CPField": "TimeChk_25km", "CPAccumulate": 19220, "unixTOD": 1734224801.25, "unixtime": 1734224801.25, "chip_time": "8979.050", "time": "09:06:41", "section_total_rank": null, "sTime": "00:23:19", "cumulativeTime": "02:29:40", "raceTime": "02:29:40", "averageRate": "05:59", "speed": 2.86, "rate": 350, "sRate": "05:49"}, "7": {"CPId": "07", "CPName": "26k", "CPDistance": 1000, "CPField": "TimeSplitM2", "CPAccumulate": 20220, "unixTOD": 1734225471.8, "unixtime": 1734225471.8, "chip_time": "9649.600", "time": "09:17:51", "section_total_rank": null, "sTime": "00:11:11", "cumulativeTime": "02:40:50", "raceTime": "02:40:50", "averageRate": "06:11", "speed": 1.49, "rate": 671, "sRate": "11:10"}, "8": {"CPId": "08", "CPName": "30k", "CPDistance": 4000, "CPField": "TimeChk_30km", "CPAccumulate": 24220, "unixTOD": 1734226580.1, "unixtime": 1734226580.1, "chip_time": "10757.900", "time": "09:36:20", "section_total_rank": null, "sTime": "00:18:29", "cumulativeTime": "02:59:18", "raceTime": "02:59:18", "averageRate": "05:58", "speed": 3.61, "rate": 277, "sRate": "04:37"}, "9": {"CPId": "09", "CPName": "35k", "CPDistance": 5000, "CPField": "TimeChk_35km", "CPAccumulate": 29220, "unixTOD": 1734228216.7, "unixtime": 1734228216.7, "chip_time": "12394.500", "time": "10:03:36", "section_total_rank": null, "sTime": "00:27:17", "cumulativeTime": "03:26:35", "raceTime": "03:26:35", "averageRate": "05:54", "speed": 3.06, "rate": 327, "sRate": "05:27"}, "10": {"CPId": "10", "CPName": "40k", "CPDistance": 5000, "CPField": "TimeChk_40km", "CPAccumulate": 34220, "unixTOD": 1734230042.5, "unixtime": 1734230042.5, "chip_time": "14220.300", "time": "10:34:02", "section_total_rank": null, "sTime": "00:30:26", "cumulativeTime": "03:57:01", "raceTime": "03:57:01", "averageRate": "05:55", "speed": 2.74, "rate": 365, "sRate": "06:05"}, "11": {"CPId": "99", "CPName": "FINISH", "CPDistance": 2195, "CPField": "TimeFinish", "CPAccumulate": 36415, "unixTOD": 1734230882.45, "unixtime": 1734230882.45, "chip_time": "15060.250", "time": "10:48:02", "section_total_rank": null, "sTime": "00:14:00", "cumulativeTime": "04:11:01", "raceTime": "04:11:01", "averageRate": "05:56", "speed": 2.61, "rate": 383, "sRate": "06:22"}}, "estimatePosition": "42.195 KM", "estimateDistance": 42195, "estimateComplete": "\u5df2\u62b5\u9054", "totalDistance": 42195, "estimatePercent": 100}}