{"runner_info": {"Bib Number": "001518", "Name": "Ng Kar Wing Rita", "Event": "MA", "Group": "\u597340-49\u6b72", "Nation": "FR", "Gender": "\u5973", "Gun Time": "04:43:50", "Net Time": "04:38:12"}, "record": {"cp": {"-1": {"CPId": "0", "CPName": "Gun Start", "CPDistance": 0, "CPField": "TimeGun", "CPAccumulate": 0, "unixTOD": 1734215400.4, "unixtime": 1734215400.4, "chip_time": 0, "time": "06:30:00", "section_total_rank": null, "sTime": "--:--:--", "cumulativeTime": "00:00:00", "raceTime": "00:00:00", "averageRate": "--:--", "sRate": "--:--"}, "0": {"CPId": "00", "CPName": "Start", "CPDistance": 0, "CPField": "TimeStart", "CPAccumulate": 0, "unixTOD": 1734215737.65, "unixtime": 1734215737.65, "chip_time": 0, "time": "06:35:37", "section_total_rank": null, "sTime": "--:--:--", "cumulativeTime": "00:00:00", "raceTime": "00:00:00", "averageRate": "--:--", "sRate": "--:--"}, "1": {"CPId": "01", "CPName": "5k", "CPDistance": 5000, "CPField": "TimeChk_05km", "CPAccumulate": 5000, "unixTOD": 1734217553.9, "unixtime": 1734217553.9, "chip_time": "1816.250", "time": "07:05:53", "section_total_rank": null, "sTime": "00:30:17", "cumulativeTime": "00:30:17", "raceTime": "00:30:17", "averageRate": "06:03", "speed": 2.75, "rate": 363, "sRate": "06:03"}, "2": {"CPId": "02", "CPName": "10k", "CPDistance": 5000, "CPField": "TimeChk_10km", "CPAccumulate": 10000, "unixTOD": 1734219361.85, "unixtime": 1734219361.85, "chip_time": "3624.200", "time": "07:36:01", "section_total_rank": null, "sTime": "00:30:08", "cumulativeTime": "01:00:25", "raceTime": "01:00:25", "averageRate": "06:02", "speed": 2.77, "rate": 362, "sRate": "06:01"}, "3": {"CPId": "03", "CPName": "15k", "CPDistance": 5000, "CPField": "TimeChk_15km", "CPAccumulate": 15000, "unixTOD": 1734221174.15, "unixtime": 1734221174.15, "chip_time": "5436.500", "time": "08:06:14", "section_total_rank": null, "sTime": "00:30:13", "cumulativeTime": "01:30:37", "raceTime": "01:30:37", "averageRate": "06:02", "speed": 2.76, "rate": 362, "sRate": "06:02"}, "4": {"CPId": "04", "CPName": "20k", "CPDistance": 5000, "CPField": "TimeChk_20km", "CPAccumulate": 20000, "unixTOD": 1734223026.25, "unixtime": 1734223026.25, "chip_time": "7288.600", "time": "08:37:06", "section_total_rank": null, "sTime": "00:30:53", "cumulativeTime": "02:01:29", "raceTime": "02:01:29", "averageRate": "06:04", "speed": 2.7, "rate": 370, "sRate": "06:10"}, "5": {"CPId": "05", "CPName": "21k", "CPDistance": 1000, "CPField": "TimeSplitM1", "CPAccumulate": 15220, "unixTOD": 1734223460.2, "unixtime": 1734223460.2, "chip_time": "7722.550", "time": "08:44:20", "section_total_rank": null, "sTime": "00:07:14", "cumulativeTime": "02:08:43", "raceTime": "02:08:43", "averageRate": "06:07", "speed": 2.3, "rate": 434, "sRate": "07:13"}, "6": {"CPId": "06", "CPName": "25k", "CPDistance": 4000, "CPField": "TimeChk_25km", "CPAccumulate": 19220, "unixTOD": 1734225018.15, "unixtime": 1734225018.15, "chip_time": "9280.500", "time": "09:10:18", "section_total_rank": null, "sTime": "00:25:58", "cumulativeTime": "02:34:41", "raceTime": "02:34:41", "averageRate": "06:11", "speed": 2.57, "rate": 389, "sRate": "06:29"}, "7": {"CPId": "07", "CPName": "26k", "CPDistance": 1000, "CPField": "TimeSplitM2", "CPAccumulate": 20220, "unixTOD": 1734225767.65, "unixtime": 1734225767.65, "chip_time": "10030.000", "time": "09:22:47", "section_total_rank": null, "sTime": "00:12:30", "cumulativeTime": "02:47:10", "raceTime": "02:47:10", "averageRate": "06:25", "speed": 1.33, "rate": 750, "sRate": "12:29"}, "8": {"CPId": "08", "CPName": "30k", "CPDistance": 4000, "CPField": "TimeChk_30km", "CPAccumulate": 24220, "unixTOD": 1734227090, "unixtime": 1734227090, "chip_time": "11352.350", "time": "09:44:50", "section_total_rank": null, "sTime": "00:22:03", "cumulativeTime": "03:09:13", "raceTime": "03:09:13", "averageRate": "06:18", "speed": 3.02, "rate": 331, "sRate": "05:30"}, "9": {"CPId": "09", "CPName": "35k", "CPDistance": 5000, "CPField": "TimeChk_35km", "CPAccumulate": 29220, "unixTOD": 1734229224.65, "unixtime": 1734229224.65, "chip_time": "13487.000", "time": "10:20:24", "section_total_rank": null, "sTime": "00:35:35", "cumulativeTime": "03:44:47", "raceTime": "03:44:47", "averageRate": "06:25", "speed": 2.34, "rate": 427, "sRate": "07:06"}, "10": {"CPId": "10", "CPName": "40k", "CPDistance": 5000, "CPField": "TimeChk_40km", "CPAccumulate": 34220, "unixTOD": 1734231488, "unixtime": 1734231488, "chip_time": "15750.350", "time": "10:58:08", "section_total_rank": null, "sTime": "00:37:44", "cumulativeTime": "04:22:31", "raceTime": "04:22:31", "averageRate": "06:33", "speed": 2.21, "rate": 453, "sRate": "07:32"}, "11": {"CPId": "99", "CPName": "FINISH", "CPDistance": 2195, "CPField": "TimeFinish", "CPAccumulate": 36415, "unixTOD": 1734232429.65, "unixtime": 1734232429.65, "chip_time": "16692.000", "time": "11:13:49", "section_total_rank": null, "sTime": "00:15:42", "cumulativeTime": "04:38:12", "raceTime": "04:38:12", "averageRate": "06:35", "speed": 2.33, "rate": 429, "sRate": "07:08"}}, "estimatePosition": "42.195 KM", "estimateDistance": 42195, "estimateComplete": "\u5df2\u62b5\u9054", "totalDistance": 42195, "estimatePercent": 100}}