{"runner_info": {"Bib Number": "002134", "Name": "\u5433\u52c7\u5100", "Event": "MA", "Group": "\u753740-49\u6b72", "Nation": "TPE", "Gender": "\u7537", "Gun Time": "03:35:16", "Net Time": "03:32:18"}, "record": {"cp": {"-1": {"CPId": "0", "CPName": "Gun Start", "CPDistance": 0, "CPField": "TimeGun", "CPAccumulate": 0, "unixTOD": 1734215400.4, "unixtime": 1734215400.4, "chip_time": 0, "time": "06:30:00", "section_total_rank": null, "sTime": "--:--:--", "cumulativeTime": "00:00:00", "raceTime": "00:00:00", "averageRate": "--:--", "sRate": "--:--"}, "0": {"CPId": "00", "CPName": "Start", "CPDistance": 0, "CPField": "TimeStart", "CPAccumulate": 0, "unixTOD": 1734215578.7, "unixtime": 1734215578.7, "chip_time": 0, "time": "06:32:58", "section_total_rank": null, "sTime": "--:--:--", "cumulativeTime": "00:00:00", "raceTime": "00:00:00", "averageRate": "--:--", "sRate": "--:--"}, "1": {"CPId": "01", "CPName": "5k", "CPDistance": 5000, "CPField": "TimeChk_05km", "CPAccumulate": 5000, "unixTOD": 1734217054.1, "unixtime": 1734217054.1, "chip_time": "1475.400", "time": "06:57:34", "section_total_rank": null, "sTime": "00:24:36", "cumulativeTime": "00:24:36", "raceTime": "00:24:36", "averageRate": "04:55", "speed": 3.39, "rate": 295, "sRate": "04:55"}, "2": {"CPId": "02", "CPName": "10k", "CPDistance": 5000, "CPField": "TimeChk_10km", "CPAccumulate": 10000, "unixTOD": 1734218497.4, "unixtime": 1734218497.4, "chip_time": "2918.700", "time": "07:21:37", "section_total_rank": null, "sTime": "00:24:04", "cumulativeTime": "00:48:39", "raceTime": "00:48:39", "averageRate": "04:51", "speed": 3.46, "rate": 289, "sRate": "04:48"}, "3": {"CPId": "03", "CPName": "15k", "CPDistance": 5000, "CPField": "TimeChk_15km", "CPAccumulate": 15000, "unixTOD": 1734219927.3, "unixtime": 1734219927.3, "chip_time": "4348.600", "time": "07:45:27", "section_total_rank": null, "sTime": "00:23:50", "cumulativeTime": "01:12:29", "raceTime": "01:12:29", "averageRate": "04:49", "speed": 3.5, "rate": 286, "sRate": "04:45"}, "4": {"CPId": "04", "CPName": "20k", "CPDistance": 5000, "CPField": "TimeChk_20km", "CPAccumulate": 20000, "unixTOD": 1734221365.85, "unixtime": 1734221365.85, "chip_time": "5787.150", "time": "08:09:25", "section_total_rank": null, "sTime": "00:23:59", "cumulativeTime": "01:36:28", "raceTime": "01:36:28", "averageRate": "04:49", "speed": 3.48, "rate": 288, "sRate": "04:47"}, "5": {"CPId": "05", "CPName": "21k", "CPDistance": 1000, "CPField": "TimeSplitM1", "CPAccumulate": 15220, "unixTOD": 1734221693.45, "unixtime": 1734221693.45, "chip_time": "6114.750", "time": "08:14:53", "section_total_rank": null, "sTime": "00:05:28", "cumulativeTime": "01:41:55", "raceTime": "01:41:55", "averageRate": "04:51", "speed": 3.05, "rate": 328, "sRate": "05:27"}, "6": {"CPId": "06", "CPName": "25k", "CPDistance": 4000, "CPField": "TimeChk_25km", "CPAccumulate": 19220, "unixTOD": 1734222848.4, "unixtime": 1734222848.4, "chip_time": "7269.700", "time": "08:34:08", "section_total_rank": null, "sTime": "00:19:15", "cumulativeTime": "02:01:10", "raceTime": "02:01:10", "averageRate": "04:50", "speed": 3.46, "rate": 289, "sRate": "04:48"}, "7": {"CPId": "07", "CPName": "26k", "CPDistance": 1000, "CPField": "TimeSplitM2", "CPAccumulate": 20220, "unixTOD": 1734223391.1, "unixtime": 1734223391.1, "chip_time": "7812.400", "time": "08:43:11", "section_total_rank": null, "sTime": "00:09:03", "cumulativeTime": "02:10:13", "raceTime": "02:10:13", "averageRate": "05:00", "speed": 1.84, "rate": 543, "sRate": "09:02"}, "8": {"CPId": "08", "CPName": "30k", "CPDistance": 4000, "CPField": "TimeChk_30km", "CPAccumulate": 24220, "unixTOD": 1734224339.4, "unixtime": 1734224339.4, "chip_time": "8760.700", "time": "08:58:59", "section_total_rank": null, "sTime": "00:15:49", "cumulativeTime": "02:26:01", "raceTime": "02:26:01", "averageRate": "04:52", "speed": 4.22, "rate": 237, "sRate": "03:57"}, "9": {"CPId": "09", "CPName": "35k", "CPDistance": 5000, "CPField": "TimeChk_35km", "CPAccumulate": 29220, "unixTOD": 1734225893.05, "unixtime": 1734225893.05, "chip_time": "10314.350", "time": "09:24:53", "section_total_rank": null, "sTime": "00:25:54", "cumulativeTime": "02:51:55", "raceTime": "02:51:55", "averageRate": "04:54", "speed": 3.22, "rate": 311, "sRate": "05:10"}, "10": {"CPId": "10", "CPName": "40k", "CPDistance": 5000, "CPField": "TimeChk_40km", "CPAccumulate": 34220, "unixTOD": 1734227589.65, "unixtime": 1734227589.65, "chip_time": "12010.950", "time": "09:53:09", "section_total_rank": null, "sTime": "00:28:17", "cumulativeTime": "03:20:11", "raceTime": "03:20:11", "averageRate": "05:00", "speed": 2.95, "rate": 339, "sRate": "05:39"}, "11": {"CPId": "99", "CPName": "FINISH", "CPDistance": 2195, "CPField": "TimeFinish", "CPAccumulate": 36415, "unixTOD": 1734228315.9, "unixtime": 1734228315.9, "chip_time": "12737.200", "time": "10:05:15", "section_total_rank": null, "sTime": "00:12:07", "cumulativeTime": "03:32:18", "raceTime": "03:32:18", "averageRate": "05:01", "speed": 3.02, "rate": 331, "sRate": "05:30"}}, "estimatePosition": "42.195 KM", "estimateDistance": 42195, "estimateComplete": "\u5df2\u62b5\u9054", "totalDistance": 42195, "estimatePercent": 100}}