{"runner_info": {"Bib Number": "004674", "Name": "\u856d\u541b\u5c55", "Event": "MA", "Group": "\u753740-49\u6b72", "Nation": "TPE", "Gender": "\u7537", "Gun Time": "04:19:38", "Net Time": "04:13:00"}, "record": {"cp": {"-1": {"CPId": "0", "CPName": "Gun Start", "CPDistance": 0, "CPField": "TimeGun", "CPAccumulate": 0, "unixTOD": 1734215400.4, "unixtime": 1734215400.4, "chip_time": 0, "time": "06:30:00", "section_total_rank": null, "sTime": "--:--:--", "cumulativeTime": "00:00:00", "raceTime": "00:00:00", "averageRate": "--:--", "sRate": "--:--"}, "0": {"CPId": "00", "CPName": "Start", "CPDistance": 0, "CPField": "TimeStart", "CPAccumulate": 0, "unixTOD": 1734215798.2, "unixtime": 1734215798.2, "chip_time": 0, "time": "06:36:38", "section_total_rank": null, "sTime": "--:--:--", "cumulativeTime": "00:00:00", "raceTime": "00:00:00", "averageRate": "--:--", "sRate": "--:--"}, "1": {"CPId": "01", "CPName": "5k", "CPDistance": 5000, "CPField": "TimeChk_05km", "CPAccumulate": 5000, "unixTOD": 1734217545.2, "unixtime": 1734217545.2, "chip_time": "1747.000", "time": "07:05:45", "section_total_rank": null, "sTime": "00:29:07", "cumulativeTime": "00:29:07", "raceTime": "00:29:07", "averageRate": "05:49", "speed": 2.86, "rate": 349, "sRate": "05:49"}, "2": {"CPId": "02", "CPName": "10k", "CPDistance": 5000, "CPField": "TimeChk_10km", "CPAccumulate": 10000, "unixTOD": 1734219315.9, "unixtime": 1734219315.9, "chip_time": "3517.700", "time": "07:35:15", "section_total_rank": null, "sTime": "00:29:31", "cumulativeTime": "00:58:38", "raceTime": "00:58:38", "averageRate": "05:51", "speed": 2.82, "rate": 354, "sRate": "05:54"}, "3": {"CPId": "03", "CPName": "15k", "CPDistance": 5000, "CPField": "TimeChk_15km", "CPAccumulate": 15000, "unixTOD": 1734221077.6, "unixtime": 1734221077.6, "chip_time": "5279.400", "time": "08:04:37", "section_total_rank": null, "sTime": "00:29:22", "cumulativeTime": "01:28:00", "raceTime": "01:28:00", "averageRate": "05:51", "speed": 2.84, "rate": 352, "sRate": "05:52"}, "4": {"CPId": "04", "CPName": "20k", "CPDistance": 5000, "CPField": "TimeChk_20km", "CPAccumulate": 20000, "unixTOD": 1734222910.6, "unixtime": 1734222910.6, "chip_time": "7112.400", "time": "08:35:10", "section_total_rank": null, "sTime": "00:30:33", "cumulativeTime": "01:58:33", "raceTime": "01:58:33", "averageRate": "05:55", "speed": 2.73, "rate": 367, "sRate": "06:06"}, "5": {"CPId": "05", "CPName": "21k", "CPDistance": 1000, "CPField": "TimeSplitM1", "CPAccumulate": 15220, "unixTOD": 1734223339.85, "unixtime": 1734223339.85, "chip_time": "7541.650", "time": "08:42:19", "section_total_rank": null, "sTime": "00:07:10", "cumulativeTime": "02:05:42", "raceTime": "02:05:42", "averageRate": "05:59", "speed": 2.33, "rate": 429, "sRate": "07:09"}, "6": {"CPId": "06", "CPName": "25k", "CPDistance": 4000, "CPField": "TimeChk_25km", "CPAccumulate": 19220, "unixTOD": 1734224819.2, "unixtime": 1734224819.2, "chip_time": "9021.000", "time": "09:06:59", "section_total_rank": null, "sTime": "00:24:40", "cumulativeTime": "02:30:21", "raceTime": "02:30:21", "averageRate": "06:00", "speed": 2.7, "rate": 370, "sRate": "06:09"}, "7": {"CPId": "07", "CPName": "26k", "CPDistance": 1000, "CPField": "TimeSplitM2", "CPAccumulate": 20220, "unixTOD": 1734225496.95, "unixtime": 1734225496.95, "chip_time": "9698.750", "time": "09:18:16", "section_total_rank": null, "sTime": "00:11:18", "cumulativeTime": "02:41:39", "raceTime": "02:41:39", "averageRate": "06:13", "speed": 1.48, "rate": 678, "sRate": "11:17"}, "8": {"CPId": "08", "CPName": "30k", "CPDistance": 4000, "CPField": "TimeChk_30km", "CPAccumulate": 24220, "unixTOD": 1734226653.6, "unixtime": 1734226653.6, "chip_time": "10855.400", "time": "09:37:33", "section_total_rank": null, "sTime": "00:19:17", "cumulativeTime": "03:00:56", "raceTime": "03:00:56", "averageRate": "06:01", "speed": 3.46, "rate": 289, "sRate": "04:49"}, "9": {"CPId": "09", "CPName": "35k", "CPDistance": 5000, "CPField": "TimeChk_35km", "CPAccumulate": 29220, "unixTOD": 1734228461.8, "unixtime": 1734228461.8, "chip_time": "12663.600", "time": "10:07:41", "section_total_rank": null, "sTime": "00:30:09", "cumulativeTime": "03:31:04", "raceTime": "03:31:04", "averageRate": "06:01", "speed": 2.77, "rate": 362, "sRate": "06:01"}, "10": {"CPId": "10", "CPName": "40k", "CPDistance": 5000, "CPField": "TimeChk_40km", "CPAccumulate": 34220, "unixTOD": 1734230244.65, "unixtime": 1734230244.65, "chip_time": "14446.450", "time": "10:37:24", "section_total_rank": null, "sTime": "00:29:43", "cumulativeTime": "04:00:47", "raceTime": "04:00:47", "averageRate": "06:01", "speed": 2.8, "rate": 357, "sRate": "05:56"}, "11": {"CPId": "99", "CPName": "FINISH", "CPDistance": 2195, "CPField": "TimeFinish", "CPAccumulate": 36415, "unixTOD": 1734230977.7, "unixtime": 1734230977.7, "chip_time": "15179.500", "time": "10:49:37", "section_total_rank": null, "sTime": "00:12:14", "cumulativeTime": "04:13:00", "raceTime": "04:13:00", "averageRate": "05:59", "speed": 2.99, "rate": 334, "sRate": "05:33"}}, "estimatePosition": "42.195 KM", "estimateDistance": 42195, "estimateComplete": "\u5df2\u62b5\u9054", "totalDistance": 42195, "estimatePercent": 100}}