{"runner_info": {"Bib Number": "005630", "Name": "\u8521\u4f51\u6771", "Event": "MA", "Group": "\u753740-49\u6b72", "Nation": "TPE", "Gender": "\u7537", "Gun Time": "04:28:50", "Net Time": "04:26:41"}, "record": {"cp": {"-1": {"CPId": "0", "CPName": "Gun Start", "CPDistance": 0, "CPField": "TimeGun", "CPAccumulate": 0, "unixTOD": 1734215400.4, "unixtime": 1734215400.4, "chip_time": 0, "time": "06:30:00", "section_total_rank": null, "sTime": "--:--:--", "cumulativeTime": "00:00:00", "raceTime": "00:00:00", "averageRate": "--:--", "sRate": "--:--"}, "0": {"CPId": "00", "CPName": "Start", "CPDistance": 0, "CPField": "TimeStart", "CPAccumulate": 0, "unixTOD": 1734215530.1, "unixtime": 1734215530.1, "chip_time": 0, "time": "06:32:10", "section_total_rank": null, "sTime": "--:--:--", "cumulativeTime": "00:00:00", "raceTime": "00:00:00", "averageRate": "--:--", "sRate": "--:--"}, "1": {"CPId": "01", "CPName": "5k", "CPDistance": 5000, "CPField": "TimeChk_05km", "CPAccumulate": 5000, "unixTOD": 1734217159.6, "unixtime": 1734217159.6, "chip_time": "1629.500", "time": "06:59:19", "section_total_rank": null, "sTime": "00:27:10", "cumulativeTime": "00:27:10", "raceTime": "00:27:10", "averageRate": "05:25", "speed": 3.07, "rate": 326, "sRate": "05:25"}, "2": {"CPId": "02", "CPName": "10k", "CPDistance": 5000, "CPField": "TimeChk_10km", "CPAccumulate": 10000, "unixTOD": 1734218780, "unixtime": 1734218780, "chip_time": "3249.900", "time": "07:26:20", "section_total_rank": null, "sTime": "00:27:01", "cumulativeTime": "00:54:10", "raceTime": "00:54:10", "averageRate": "05:24", "speed": 3.09, "rate": 324, "sRate": "05:24"}, "3": {"CPId": "03", "CPName": "15k", "CPDistance": 5000, "CPField": "TimeChk_15km", "CPAccumulate": 15000, "unixTOD": 1734220394.65, "unixtime": 1734220394.65, "chip_time": "4864.550", "time": "07:53:14", "section_total_rank": null, "sTime": "00:26:55", "cumulativeTime": "01:21:05", "raceTime": "01:21:05", "averageRate": "05:24", "speed": 3.1, "rate": 323, "sRate": "05:22"}, "4": {"CPId": "04", "CPName": "20k", "CPDistance": 5000, "CPField": "TimeChk_20km", "CPAccumulate": 20000, "unixTOD": 1734222024.15, "unixtime": 1734222024.15, "chip_time": "6494.050", "time": "08:20:24", "section_total_rank": null, "sTime": "00:27:10", "cumulativeTime": "01:48:15", "raceTime": "01:48:15", "averageRate": "05:24", "speed": 3.07, "rate": 326, "sRate": "05:25"}, "5": {"CPId": "05", "CPName": "21k", "CPDistance": 1000, "CPField": "TimeSplitM1", "CPAccumulate": 15220, "unixTOD": 1734222403.45, "unixtime": 1734222403.45, "chip_time": "6873.350", "time": "08:26:43", "section_total_rank": null, "sTime": "00:06:20", "cumulativeTime": "01:54:34", "raceTime": "01:54:34", "averageRate": "05:27", "speed": 2.64, "rate": 379, "sRate": "06:19"}, "6": {"CPId": "06", "CPName": "25k", "CPDistance": 4000, "CPField": "TimeChk_25km", "CPAccumulate": 19220, "unixTOD": 1734223733.95, "unixtime": 1734223733.95, "chip_time": "8203.850", "time": "08:48:53", "section_total_rank": null, "sTime": "00:22:11", "cumulativeTime": "02:16:44", "raceTime": "02:16:44", "averageRate": "05:28", "speed": 3.01, "rate": 333, "sRate": "05:32"}, "7": {"CPId": "07", "CPName": "26k", "CPDistance": 1000, "CPField": "TimeSplitM2", "CPAccumulate": 20220, "unixTOD": 1734224427.45, "unixtime": 1734224427.45, "chip_time": "8897.350", "time": "09:00:27", "section_total_rank": null, "sTime": "00:11:34", "cumulativeTime": "02:28:18", "raceTime": "02:28:18", "averageRate": "05:42", "speed": 1.44, "rate": 694, "sRate": "11:33"}, "8": {"CPId": "08", "CPName": "30k", "CPDistance": 4000, "CPField": "TimeChk_30km", "CPAccumulate": 24220, "unixTOD": 1734225678, "unixtime": 1734225678, "chip_time": "10147.900", "time": "09:21:18", "section_total_rank": null, "sTime": "00:20:51", "cumulativeTime": "02:49:08", "raceTime": "02:49:08", "averageRate": "05:38", "speed": 3.2, "rate": 313, "sRate": "05:12"}, "9": {"CPId": "09", "CPName": "35k", "CPDistance": 5000, "CPField": "TimeChk_35km", "CPAccumulate": 29220, "unixTOD": 1734227913.4, "unixtime": 1734227913.4, "chip_time": "12383.300", "time": "09:58:33", "section_total_rank": null, "sTime": "00:37:16", "cumulativeTime": "03:26:24", "raceTime": "03:26:24", "averageRate": "05:53", "speed": 2.24, "rate": 447, "sRate": "07:27"}, "10": {"CPId": "10", "CPName": "40k", "CPDistance": 5000, "CPField": "TimeChk_40km", "CPAccumulate": 34220, "unixTOD": 1734230507.75, "unixtime": 1734230507.75, "chip_time": "14977.650", "time": "10:41:47", "section_total_rank": null, "sTime": "00:43:15", "cumulativeTime": "04:09:38", "raceTime": "04:09:38", "averageRate": "06:14", "speed": 1.93, "rate": 519, "sRate": "08:38"}, "11": {"CPId": "99", "CPName": "FINISH", "CPDistance": 2195, "CPField": "TimeFinish", "CPAccumulate": 36415, "unixTOD": 1734231530.2, "unixtime": 1734231530.2, "chip_time": "16000.100", "time": "10:58:50", "section_total_rank": null, "sTime": "00:17:03", "cumulativeTime": "04:26:41", "raceTime": "04:26:41", "averageRate": "06:19", "speed": 2.15, "rate": 466, "sRate": "07:45"}}, "estimatePosition": "42.195 KM", "estimateDistance": 42195, "estimateComplete": "\u5df2\u62b5\u9054", "totalDistance": 42195, "estimatePercent": 100}}