{"runner_info": {"Bib Number": "006377", "Name": "\u76e7\u51a0\u5b87", "Event": "MA", "Group": "\u753720-29\u6b72", "Nation": "TPE", "Gender": "\u7537", "Gun Time": "03:01:30", "Net Time": "03:00:28"}, "record": {"cp": {"-1": {"CPId": "0", "CPName": "Gun Start", "CPDistance": 0, "CPField": "TimeGun", "CPAccumulate": 0, "unixTOD": 1734215400.4, "unixtime": 1734215400.4, "chip_time": 0, "time": "06:30:00", "section_total_rank": null, "sTime": "--:--:--", "cumulativeTime": "00:00:00", "raceTime": "00:00:00", "averageRate": "--:--", "sRate": "--:--"}, "0": {"CPId": "00", "CPName": "Start", "CPDistance": 0, "CPField": "TimeStart", "CPAccumulate": 0, "unixTOD": 1734215462, "unixtime": 1734215462, "chip_time": 0, "time": "06:31:02", "section_total_rank": null, "sTime": "--:--:--", "cumulativeTime": "00:00:00", "raceTime": "00:00:00", "averageRate": "--:--", "sRate": "--:--"}, "1": {"CPId": "01", "CPName": "5k", "CPDistance": 5000, "CPField": "TimeChk_05km", "CPAccumulate": 5000, "unixTOD": 1734216723.5, "unixtime": 1734216723.5, "chip_time": "1261.500", "time": "06:52:03", "section_total_rank": null, "sTime": "00:21:02", "cumulativeTime": "00:21:02", "raceTime": "00:21:02", "averageRate": "04:12", "speed": 3.96, "rate": 252, "sRate": "04:12"}, "2": {"CPId": "02", "CPName": "10k", "CPDistance": 5000, "CPField": "TimeChk_10km", "CPAccumulate": 10000, "unixTOD": 1734217975.65, "unixtime": 1734217975.65, "chip_time": "2513.650", "time": "07:12:55", "section_total_rank": null, "sTime": "00:20:53", "cumulativeTime": "00:41:54", "raceTime": "00:41:54", "averageRate": "04:11", "speed": 3.99, "rate": 250, "sRate": "04:10"}, "3": {"CPId": "03", "CPName": "15k", "CPDistance": 5000, "CPField": "TimeChk_15km", "CPAccumulate": 15000, "unixTOD": 1734219247.45, "unixtime": 1734219247.45, "chip_time": "3785.450", "time": "07:34:07", "section_total_rank": null, "sTime": "00:21:12", "cumulativeTime": "01:03:06", "raceTime": "01:03:06", "averageRate": "04:12", "speed": 3.93, "rate": 254, "sRate": "04:14"}, "4": {"CPId": "04", "CPName": "20k", "CPDistance": 5000, "CPField": "TimeChk_20km", "CPAccumulate": 20000, "unixTOD": 1734220661.45, "unixtime": 1734220661.45, "chip_time": "5199.450", "time": "07:57:41", "section_total_rank": null, "sTime": "00:23:34", "cumulativeTime": "01:26:40", "raceTime": "01:26:40", "averageRate": "04:19", "speed": 3.54, "rate": 283, "sRate": "04:42"}, "5": {"CPId": "05", "CPName": "21k", "CPDistance": 1000, "CPField": "TimeSplitM1", "CPAccumulate": 15220, "unixTOD": 1734220939.45, "unixtime": 1734220939.45, "chip_time": "5477.450", "time": "08:02:19", "section_total_rank": null, "sTime": "00:04:38", "cumulativeTime": "01:31:18", "raceTime": "01:31:18", "averageRate": "04:20", "speed": 3.6, "rate": 278, "sRate": "04:38"}, "6": {"CPId": "06", "CPName": "25k", "CPDistance": 4000, "CPField": "TimeChk_25km", "CPAccumulate": 19220, "unixTOD": 1734221936.55, "unixtime": 1734221936.55, "chip_time": "6474.550", "time": "08:18:56", "section_total_rank": null, "sTime": "00:16:38", "cumulativeTime": "01:47:55", "raceTime": "01:47:55", "averageRate": "04:18", "speed": 4.01, "rate": 249, "sRate": "04:09"}, "7": {"CPId": "07", "CPName": "26k", "CPDistance": 1000, "CPField": "TimeSplitM2", "CPAccumulate": 20220, "unixTOD": 1734222403.65, "unixtime": 1734222403.65, "chip_time": "6941.650", "time": "08:26:43", "section_total_rank": null, "sTime": "00:07:48", "cumulativeTime": "01:55:42", "raceTime": "01:55:42", "averageRate": "04:26", "speed": 2.14, "rate": 467, "sRate": "07:47"}, "8": {"CPId": "08", "CPName": "30k", "CPDistance": 4000, "CPField": "TimeChk_30km", "CPAccumulate": 24220, "unixTOD": 1734223212.9, "unixtime": 1734223212.9, "chip_time": "7750.900", "time": "08:40:12", "section_total_rank": null, "sTime": "00:13:30", "cumulativeTime": "02:09:11", "raceTime": "02:09:11", "averageRate": "04:18", "speed": 4.94, "rate": 202, "sRate": "03:22"}, "9": {"CPId": "09", "CPName": "35k", "CPDistance": 5000, "CPField": "TimeChk_35km", "CPAccumulate": 29220, "unixTOD": 1734224483.15, "unixtime": 1734224483.15, "chip_time": "9021.150", "time": "09:01:23", "section_total_rank": null, "sTime": "00:21:11", "cumulativeTime": "02:30:22", "raceTime": "02:30:22", "averageRate": "04:17", "speed": 3.94, "rate": 254, "sRate": "04:14"}, "10": {"CPId": "10", "CPName": "40k", "CPDistance": 5000, "CPField": "TimeChk_40km", "CPAccumulate": 34220, "unixTOD": 1734225728, "unixtime": 1734225728, "chip_time": "10266.000", "time": "09:22:08", "section_total_rank": null, "sTime": "00:20:45", "cumulativeTime": "02:51:06", "raceTime": "02:51:06", "averageRate": "04:16", "speed": 4.02, "rate": 249, "sRate": "04:08"}, "11": {"CPId": "99", "CPName": "FINISH", "CPDistance": 2195, "CPField": "TimeFinish", "CPAccumulate": 36415, "unixTOD": 1734226289.7, "unixtime": 1734226289.7, "chip_time": "10827.700", "time": "09:31:29", "section_total_rank": null, "sTime": "00:09:22", "cumulativeTime": "03:00:28", "raceTime": "03:00:28", "averageRate": "04:16", "speed": 3.91, "rate": 256, "sRate": "04:15"}}, "estimatePosition": "42.195 KM", "estimateDistance": 42195, "estimateComplete": "\u5df2\u62b5\u9054", "totalDistance": 42195, "estimatePercent": 100}}