{"runner_info": {"Bib Number": "006682", "Name": "Jason Natanael", "Event": "MA", "Group": "\u753720-29\u6b72", "Nation": "TW", "Gender": "\u7537", "Gun Time": "05:12:15", "Net Time": "05:06:43"}, "record": {"cp": {"-1": {"CPId": "0", "CPName": "Gun Start", "CPDistance": 0, "CPField": "TimeGun", "CPAccumulate": 0, "unixTOD": 1734215400.4, "unixtime": 1734215400.4, "chip_time": 0, "time": "06:30:00", "section_total_rank": null, "sTime": "--:--:--", "cumulativeTime": "00:00:00", "raceTime": "00:00:00", "averageRate": "--:--", "sRate": "--:--"}, "0": {"CPId": "00", "CPName": "Start", "CPDistance": 0, "CPField": "TimeStart", "CPAccumulate": 0, "unixTOD": 1734215731.75, "unixtime": 1734215731.75, "chip_time": 0, "time": "06:35:31", "section_total_rank": null, "sTime": "--:--:--", "cumulativeTime": "00:00:00", "raceTime": "00:00:00", "averageRate": "--:--", "sRate": "--:--"}, "1": {"CPId": "01", "CPName": "5k", "CPDistance": 5000, "CPField": "TimeChk_05km", "CPAccumulate": 5000, "unixTOD": 1734217591.7, "unixtime": 1734217591.7, "chip_time": "1859.950", "time": "07:06:31", "section_total_rank": null, "sTime": "00:31:00", "cumulativeTime": "00:31:00", "raceTime": "00:31:00", "averageRate": "06:11", "speed": 2.69, "rate": 372, "sRate": "06:11"}, "2": {"CPId": "02", "CPName": "10k", "CPDistance": 5000, "CPField": "TimeChk_10km", "CPAccumulate": 10000, "unixTOD": 1734219540.05, "unixtime": 1734219540.05, "chip_time": "3808.300", "time": "07:39:00", "section_total_rank": null, "sTime": "00:32:29", "cumulativeTime": "01:03:29", "raceTime": "01:03:29", "averageRate": "06:20", "speed": 2.57, "rate": 390, "sRate": "06:29"}, "3": {"CPId": "03", "CPName": "15k", "CPDistance": 5000, "CPField": "TimeChk_15km", "CPAccumulate": 15000, "unixTOD": 1734221396.35, "unixtime": 1734221396.35, "chip_time": "5664.600", "time": "08:09:56", "section_total_rank": null, "sTime": "00:30:57", "cumulativeTime": "01:34:25", "raceTime": "01:34:25", "averageRate": "06:17", "speed": 2.69, "rate": 371, "sRate": "06:11"}, "4": {"CPId": "04", "CPName": "20k", "CPDistance": 5000, "CPField": "TimeChk_20km", "CPAccumulate": 20000, "unixTOD": 1734223498.2, "unixtime": 1734223498.2, "chip_time": "7766.450", "time": "08:44:58", "section_total_rank": null, "sTime": "00:35:02", "cumulativeTime": "02:09:27", "raceTime": "02:09:27", "averageRate": "06:28", "speed": 2.38, "rate": 420, "sRate": "07:00"}, "5": {"CPId": "05", "CPName": "21k", "CPDistance": 1000, "CPField": "TimeSplitM1", "CPAccumulate": 15220, "unixTOD": 1734224096.35, "unixtime": 1734224096.35, "chip_time": "8364.600", "time": "08:54:56", "section_total_rank": null, "sTime": "00:09:59", "cumulativeTime": "02:19:25", "raceTime": "02:19:25", "averageRate": "06:38", "speed": 1.67, "rate": 598, "sRate": "09:58"}, "6": {"CPId": "06", "CPName": "25k", "CPDistance": 4000, "CPField": "TimeChk_25km", "CPAccumulate": 19220, "unixTOD": 1734225739.9, "unixtime": 1734225739.9, "chip_time": "10008.150", "time": "09:22:19", "section_total_rank": null, "sTime": "00:27:24", "cumulativeTime": "02:46:49", "raceTime": "02:46:49", "averageRate": "06:40", "speed": 2.43, "rate": 411, "sRate": "06:50"}, "7": {"CPId": "07", "CPName": "26k", "CPDistance": 1000, "CPField": "TimeSplitM2", "CPAccumulate": 20220, "unixTOD": 1734226734.05, "unixtime": 1734226734.05, "chip_time": "11002.300", "time": "09:38:54", "section_total_rank": null, "sTime": "00:16:35", "cumulativeTime": "03:03:23", "raceTime": "03:03:23", "averageRate": "07:03", "speed": 1.01, "rate": 994, "sRate": "16:34"}, "8": {"CPId": "08", "CPName": "30k", "CPDistance": 4000, "CPField": "TimeChk_30km", "CPAccumulate": 24220, "unixTOD": 1734228408.9, "unixtime": 1734228408.9, "chip_time": "12677.150", "time": "10:06:48", "section_total_rank": null, "sTime": "00:27:55", "cumulativeTime": "03:31:18", "raceTime": "03:31:18", "averageRate": "07:02", "speed": 2.39, "rate": 419, "sRate": "06:58"}, "9": {"CPId": "09", "CPName": "35k", "CPDistance": 5000, "CPField": "TimeChk_35km", "CPAccumulate": 29220, "unixTOD": 1734230843.85, "unixtime": 1734230843.85, "chip_time": "15112.100", "time": "10:47:23", "section_total_rank": null, "sTime": "00:40:35", "cumulativeTime": "04:11:53", "raceTime": "04:11:53", "averageRate": "07:11", "speed": 2.05, "rate": 487, "sRate": "08:06"}, "10": {"CPId": "10", "CPName": "40k", "CPDistance": 5000, "CPField": "TimeChk_40km", "CPAccumulate": 34220, "unixTOD": 1734233165.5, "unixtime": 1734233165.5, "chip_time": "17433.750", "time": "11:26:05", "section_total_rank": null, "sTime": "00:38:42", "cumulativeTime": "04:50:34", "raceTime": "04:50:34", "averageRate": "07:15", "speed": 2.15, "rate": 464, "sRate": "07:44"}, "11": {"CPId": "99", "CPName": "FINISH", "CPDistance": 2195, "CPField": "TimeFinish", "CPAccumulate": 36415, "unixTOD": 1734234134.65, "unixtime": 1734234134.65, "chip_time": "18402.900", "time": "11:42:14", "section_total_rank": null, "sTime": "00:16:10", "cumulativeTime": "05:06:43", "raceTime": "05:06:43", "averageRate": "07:16", "speed": 2.26, "rate": 442, "sRate": "07:21"}}, "estimatePosition": "42.195 KM", "estimateDistance": 42195, "estimateComplete": "\u5df2\u62b5\u9054", "totalDistance": 42195, "estimatePercent": 100}}