{"runner_info": {"Bib Number": "007268", "Name": "\u7fc1\u76f8\u64c7", "Event": "MA", "Group": "\u753750-59\u6b72", "Nation": "TPE", "Gender": "\u7537", "Gun Time": "02:39:30", "Net Time": "02:39:25"}, "record": {"cp": {"-1": {"CPId": "0", "CPName": "Gun Start", "CPDistance": 0, "CPField": "TimeGun", "CPAccumulate": 0, "unixTOD": 1734215400.4, "unixtime": 1734215400.4, "chip_time": 0, "time": "06:30:00", "section_total_rank": null, "sTime": "--:--:--", "cumulativeTime": "00:00:00", "raceTime": "00:00:00", "averageRate": "--:--", "sRate": "--:--"}, "0": {"CPId": "00", "CPName": "Start", "CPDistance": 0, "CPField": "TimeStart", "CPAccumulate": 0, "unixTOD": 1734215405.25, "unixtime": 1734215405.25, "chip_time": 0, "time": "06:30:05", "section_total_rank": null, "sTime": "--:--:--", "cumulativeTime": "00:00:00", "raceTime": "00:00:00", "averageRate": "--:--", "sRate": "--:--"}, "1": {"CPId": "01", "CPName": "5k", "CPDistance": 5000, "CPField": "TimeChk_05km", "CPAccumulate": 5000, "unixTOD": 1734216525.25, "unixtime": 1734216525.25, "chip_time": "1120.000", "time": "06:48:45", "section_total_rank": null, "sTime": "00:18:40", "cumulativeTime": "00:18:40", "raceTime": "00:18:40", "averageRate": "03:44", "speed": 4.46, "rate": 224, "sRate": "03:44"}, "2": {"CPId": "02", "CPName": "10k", "CPDistance": 5000, "CPField": "TimeChk_10km", "CPAccumulate": 10000, "unixTOD": 1734217645.4, "unixtime": 1734217645.4, "chip_time": "2240.150", "time": "07:07:25", "section_total_rank": null, "sTime": "00:18:41", "cumulativeTime": "00:37:21", "raceTime": "00:37:21", "averageRate": "03:44", "speed": 4.46, "rate": 224, "sRate": "03:44"}, "3": {"CPId": "03", "CPName": "15k", "CPDistance": 5000, "CPField": "TimeChk_15km", "CPAccumulate": 15000, "unixTOD": 1734218754.4, "unixtime": 1734218754.4, "chip_time": "3349.150", "time": "07:25:54", "section_total_rank": null, "sTime": "00:18:29", "cumulativeTime": "00:55:50", "raceTime": "00:55:50", "averageRate": "03:43", "speed": 4.51, "rate": 222, "sRate": "03:41"}, "4": {"CPId": "04", "CPName": "20k", "CPDistance": 5000, "CPField": "TimeChk_20km", "CPAccumulate": 20000, "unixTOD": 1734219887.15, "unixtime": 1734219887.15, "chip_time": "4481.900", "time": "07:44:47", "section_total_rank": null, "sTime": "00:18:53", "cumulativeTime": "01:14:42", "raceTime": "01:14:42", "averageRate": "03:44", "speed": 4.41, "rate": 227, "sRate": "03:46"}, "5": {"CPId": "05", "CPName": "21k", "CPDistance": 1000, "CPField": "TimeSplitM1", "CPAccumulate": 15220, "unixTOD": 1734220139.15, "unixtime": 1734220139.15, "chip_time": "4733.900", "time": "07:48:59", "section_total_rank": null, "sTime": "00:04:12", "cumulativeTime": "01:18:54", "raceTime": "01:18:54", "averageRate": "03:45", "speed": 3.97, "rate": 252, "sRate": "04:12"}, "6": {"CPId": "06", "CPName": "25k", "CPDistance": 4000, "CPField": "TimeChk_25km", "CPAccumulate": 19220, "unixTOD": 1734221045.35, "unixtime": 1734221045.35, "chip_time": "5640.100", "time": "08:04:05", "section_total_rank": null, "sTime": "00:15:07", "cumulativeTime": "01:34:01", "raceTime": "01:34:01", "averageRate": "03:45", "speed": 4.41, "rate": 227, "sRate": "03:46"}, "7": {"CPId": "07", "CPName": "26k", "CPDistance": 1000, "CPField": "TimeSplitM2", "CPAccumulate": 20220, "unixTOD": 1734221466.3, "unixtime": 1734221466.3, "chip_time": "6061.050", "time": "08:11:06", "section_total_rank": null, "sTime": "00:07:01", "cumulativeTime": "01:41:02", "raceTime": "01:41:02", "averageRate": "03:53", "speed": 2.38, "rate": 421, "sRate": "07:00"}, "8": {"CPId": "08", "CPName": "30k", "CPDistance": 4000, "CPField": "TimeChk_30km", "CPAccumulate": 24220, "unixTOD": 1734222195.45, "unixtime": 1734222195.45, "chip_time": "6790.200", "time": "08:23:15", "section_total_rank": null, "sTime": "00:12:10", "cumulativeTime": "01:53:11", "raceTime": "01:53:11", "averageRate": "03:46", "speed": 5.49, "rate": 182, "sRate": "03:02"}, "9": {"CPId": "09", "CPName": "35k", "CPDistance": 5000, "CPField": "TimeChk_35km", "CPAccumulate": 29220, "unixTOD": 1734223328.6, "unixtime": 1734223328.6, "chip_time": "7923.350", "time": "08:42:08", "section_total_rank": null, "sTime": "00:18:54", "cumulativeTime": "02:12:04", "raceTime": "02:12:04", "averageRate": "03:46", "speed": 4.41, "rate": 227, "sRate": "03:46"}, "10": {"CPId": "10", "CPName": "40k", "CPDistance": 5000, "CPField": "TimeChk_40km", "CPAccumulate": 34220, "unixTOD": 1734224479.35, "unixtime": 1734224479.35, "chip_time": "9074.100", "time": "09:01:19", "section_total_rank": null, "sTime": "00:19:11", "cumulativeTime": "02:31:15", "raceTime": "02:31:15", "averageRate": "03:46", "speed": 4.34, "rate": 230, "sRate": "03:50"}, "11": {"CPId": "99", "CPName": "FINISH", "CPDistance": 2195, "CPField": "TimeFinish", "CPAccumulate": 36415, "unixTOD": 1734224969.9, "unixtime": 1734224969.9, "chip_time": "9564.650", "time": "09:09:29", "section_total_rank": null, "sTime": "00:08:11", "cumulativeTime": "02:39:25", "raceTime": "02:39:25", "averageRate": "03:46", "speed": 4.47, "rate": 223, "sRate": "03:43"}}, "estimatePosition": "42.195 KM", "estimateDistance": 42195, "estimateComplete": "\u5df2\u62b5\u9054", "totalDistance": 42195, "estimatePercent": 100}}