{"runner_info": {"Bib Number": "008033", "Name": "\u9ec3\u8056\u60df", "Event": "MA", "Group": "\u753730-39\u6b72", "Nation": "TPE", "Gender": "\u7537", "Gun Time": "02:55:44", "Net Time": "02:55:31"}, "record": {"cp": {"-1": {"CPId": "0", "CPName": "Gun Start", "CPDistance": 0, "CPField": "TimeGun", "CPAccumulate": 0, "unixTOD": 1734215400.4, "unixtime": 1734215400.4, "chip_time": 0, "time": "06:30:00", "section_total_rank": null, "sTime": "--:--:--", "cumulativeTime": "00:00:00", "raceTime": "00:00:00", "averageRate": "--:--", "sRate": "--:--"}, "0": {"CPId": "00", "CPName": "Start", "CPDistance": 0, "CPField": "TimeStart", "CPAccumulate": 0, "unixTOD": 1734215413.85, "unixtime": 1734215413.85, "chip_time": 0, "time": "06:30:13", "section_total_rank": null, "sTime": "--:--:--", "cumulativeTime": "00:00:00", "raceTime": "00:00:00", "averageRate": "--:--", "sRate": "--:--"}, "1": {"CPId": "01", "CPName": "5k", "CPDistance": 5000, "CPField": "TimeChk_05km", "CPAccumulate": 5000, "unixTOD": 1734216683.05, "unixtime": 1734216683.05, "chip_time": "1269.200", "time": "06:51:23", "section_total_rank": null, "sTime": "00:21:10", "cumulativeTime": "00:21:10", "raceTime": "00:21:10", "averageRate": "04:13", "speed": 3.94, "rate": 254, "sRate": "04:13"}, "2": {"CPId": "02", "CPName": "10k", "CPDistance": 5000, "CPField": "TimeChk_10km", "CPAccumulate": 10000, "unixTOD": 1734217956.1, "unixtime": 1734217956.1, "chip_time": "2542.250", "time": "07:12:36", "section_total_rank": null, "sTime": "00:21:14", "cumulativeTime": "00:42:23", "raceTime": "00:42:23", "averageRate": "04:14", "speed": 3.93, "rate": 255, "sRate": "04:14"}, "3": {"CPId": "03", "CPName": "15k", "CPDistance": 5000, "CPField": "TimeChk_15km", "CPAccumulate": 15000, "unixTOD": 1734219169.5, "unixtime": 1734219169.5, "chip_time": "3755.650", "time": "07:32:49", "section_total_rank": null, "sTime": "00:20:14", "cumulativeTime": "01:02:36", "raceTime": "01:02:36", "averageRate": "04:10", "speed": 4.12, "rate": 243, "sRate": "04:02"}, "4": {"CPId": "04", "CPName": "20k", "CPDistance": 5000, "CPField": "TimeChk_20km", "CPAccumulate": 20000, "unixTOD": 1734220383.45, "unixtime": 1734220383.45, "chip_time": "4969.600", "time": "07:53:03", "section_total_rank": null, "sTime": "00:20:14", "cumulativeTime": "01:22:50", "raceTime": "01:22:50", "averageRate": "04:08", "speed": 4.12, "rate": 243, "sRate": "04:02"}, "5": {"CPId": "05", "CPName": "21k", "CPDistance": 1000, "CPField": "TimeSplitM1", "CPAccumulate": 15220, "unixTOD": 1734220655.65, "unixtime": 1734220655.65, "chip_time": "5241.800", "time": "07:57:35", "section_total_rank": null, "sTime": "00:04:33", "cumulativeTime": "01:27:22", "raceTime": "01:27:22", "averageRate": "04:09", "speed": 3.67, "rate": 272, "sRate": "04:32"}, "6": {"CPId": "06", "CPName": "25k", "CPDistance": 4000, "CPField": "TimeChk_25km", "CPAccumulate": 19220, "unixTOD": 1734221617.4, "unixtime": 1734221617.4, "chip_time": "6203.550", "time": "08:13:37", "section_total_rank": null, "sTime": "00:16:02", "cumulativeTime": "01:43:24", "raceTime": "01:43:24", "averageRate": "04:08", "speed": 4.16, "rate": 240, "sRate": "04:00"}, "7": {"CPId": "07", "CPName": "26k", "CPDistance": 1000, "CPField": "TimeSplitM2", "CPAccumulate": 20220, "unixTOD": 1734222069.3, "unixtime": 1734222069.3, "chip_time": "6655.450", "time": "08:21:09", "section_total_rank": null, "sTime": "00:07:32", "cumulativeTime": "01:50:56", "raceTime": "01:50:56", "averageRate": "04:15", "speed": 2.21, "rate": 452, "sRate": "07:31"}, "8": {"CPId": "08", "CPName": "30k", "CPDistance": 4000, "CPField": "TimeChk_30km", "CPAccumulate": 24220, "unixTOD": 1734222857.15, "unixtime": 1734222857.15, "chip_time": "7443.300", "time": "08:34:17", "section_total_rank": null, "sTime": "00:13:08", "cumulativeTime": "02:04:04", "raceTime": "02:04:04", "averageRate": "04:08", "speed": 5.08, "rate": 197, "sRate": "03:16"}, "9": {"CPId": "09", "CPName": "35k", "CPDistance": 5000, "CPField": "TimeChk_35km", "CPAccumulate": 29220, "unixTOD": 1734224128.65, "unixtime": 1734224128.65, "chip_time": "8714.800", "time": "08:55:28", "section_total_rank": null, "sTime": "00:21:12", "cumulativeTime": "02:25:15", "raceTime": "02:25:15", "averageRate": "04:08", "speed": 3.93, "rate": 254, "sRate": "04:14"}, "10": {"CPId": "10", "CPName": "40k", "CPDistance": 5000, "CPField": "TimeChk_40km", "CPAccumulate": 34220, "unixTOD": 1734225362.85, "unixtime": 1734225362.85, "chip_time": "9949.000", "time": "09:16:02", "section_total_rank": null, "sTime": "00:20:35", "cumulativeTime": "02:45:49", "raceTime": "02:45:49", "averageRate": "04:08", "speed": 4.05, "rate": 247, "sRate": "04:06"}, "11": {"CPId": "99", "CPName": "FINISH", "CPDistance": 2195, "CPField": "TimeFinish", "CPAccumulate": 36415, "unixTOD": 1734225943.9, "unixtime": 1734225943.9, "chip_time": "10530.050", "time": "09:25:43", "section_total_rank": null, "sTime": "00:09:42", "cumulativeTime": "02:55:31", "raceTime": "02:55:31", "averageRate": "04:09", "speed": 3.78, "rate": 265, "sRate": "04:24"}}, "estimatePosition": "42.195 KM", "estimateDistance": 42195, "estimateComplete": "\u5df2\u62b5\u9054", "totalDistance": 42195, "estimatePercent": 100}}