{"runner_info": {"Bib Number": "008052", "Name": "\u8521\u74a5\u7965", "Event": "MA", "Group": "\u753730-39\u6b72", "Nation": "TPE", "Gender": "\u7537", "Gun Time": "03:01:09", "Net Time": "03:00:47"}, "record": {"cp": {"-1": {"CPId": "0", "CPName": "Gun Start", "CPDistance": 0, "CPField": "TimeGun", "CPAccumulate": 0, "unixTOD": 1734215400.4, "unixtime": 1734215400.4, "chip_time": 0, "time": "06:30:00", "section_total_rank": null, "sTime": "--:--:--", "cumulativeTime": "00:00:00", "raceTime": "00:00:00", "averageRate": "--:--", "sRate": "--:--"}, "0": {"CPId": "00", "CPName": "Start", "CPDistance": 0, "CPField": "TimeStart", "CPAccumulate": 0, "unixTOD": 1734215422.85, "unixtime": 1734215422.85, "chip_time": 0, "time": "06:30:22", "section_total_rank": null, "sTime": "--:--:--", "cumulativeTime": "00:00:00", "raceTime": "00:00:00", "averageRate": "--:--", "sRate": "--:--"}, "1": {"CPId": "01", "CPName": "5k", "CPDistance": 5000, "CPField": "TimeChk_05km", "CPAccumulate": 5000, "unixTOD": 1734216673.05, "unixtime": 1734216673.05, "chip_time": "1250.200", "time": "06:51:13", "section_total_rank": null, "sTime": "00:20:51", "cumulativeTime": "00:20:51", "raceTime": "00:20:51", "averageRate": "04:10", "speed": 4, "rate": 250, "sRate": "04:10"}, "2": {"CPId": "02", "CPName": "10k", "CPDistance": 5000, "CPField": "TimeChk_10km", "CPAccumulate": 10000, "unixTOD": 1734217943.9, "unixtime": 1734217943.9, "chip_time": "2521.050", "time": "07:12:23", "section_total_rank": null, "sTime": "00:21:11", "cumulativeTime": "00:42:02", "raceTime": "00:42:02", "averageRate": "04:12", "speed": 3.93, "rate": 254, "sRate": "04:14"}, "3": {"CPId": "03", "CPName": "15k", "CPDistance": 5000, "CPField": "TimeChk_15km", "CPAccumulate": 15000, "unixTOD": 1734219220.3, "unixtime": 1734219220.3, "chip_time": "3797.450", "time": "07:33:40", "section_total_rank": null, "sTime": "00:21:17", "cumulativeTime": "01:03:18", "raceTime": "01:03:18", "averageRate": "04:13", "speed": 3.92, "rate": 255, "sRate": "04:15"}, "4": {"CPId": "04", "CPName": "20k", "CPDistance": 5000, "CPField": "TimeChk_20km", "CPAccumulate": 20000, "unixTOD": 1734220494.45, "unixtime": 1734220494.45, "chip_time": "5071.600", "time": "07:54:54", "section_total_rank": null, "sTime": "00:21:15", "cumulativeTime": "01:24:32", "raceTime": "01:24:32", "averageRate": "04:13", "speed": 3.92, "rate": 255, "sRate": "04:14"}, "5": {"CPId": "05", "CPName": "21k", "CPDistance": 1000, "CPField": "TimeSplitM1", "CPAccumulate": 15220, "unixTOD": 1734220782.1, "unixtime": 1734220782.1, "chip_time": "5359.250", "time": "07:59:42", "section_total_rank": null, "sTime": "00:04:48", "cumulativeTime": "01:29:20", "raceTime": "01:29:20", "averageRate": "04:15", "speed": 3.48, "rate": 288, "sRate": "04:47"}, "6": {"CPId": "06", "CPName": "25k", "CPDistance": 4000, "CPField": "TimeChk_25km", "CPAccumulate": 19220, "unixTOD": 1734221785.85, "unixtime": 1734221785.85, "chip_time": "6363.000", "time": "08:16:25", "section_total_rank": null, "sTime": "00:16:44", "cumulativeTime": "01:46:03", "raceTime": "01:46:03", "averageRate": "04:14", "speed": 3.99, "rate": 251, "sRate": "04:10"}, "7": {"CPId": "07", "CPName": "26k", "CPDistance": 1000, "CPField": "TimeSplitM2", "CPAccumulate": 20220, "unixTOD": 1734222261.2, "unixtime": 1734222261.2, "chip_time": "6838.350", "time": "08:24:21", "section_total_rank": null, "sTime": "00:07:56", "cumulativeTime": "01:53:59", "raceTime": "01:53:59", "averageRate": "04:23", "speed": 2.1, "rate": 475, "sRate": "07:55"}, "8": {"CPId": "08", "CPName": "30k", "CPDistance": 4000, "CPField": "TimeChk_30km", "CPAccumulate": 24220, "unixTOD": 1734223068.45, "unixtime": 1734223068.45, "chip_time": "7645.600", "time": "08:37:48", "section_total_rank": null, "sTime": "00:13:28", "cumulativeTime": "02:07:26", "raceTime": "02:07:26", "averageRate": "04:14", "speed": 4.96, "rate": 202, "sRate": "03:21"}, "9": {"CPId": "09", "CPName": "35k", "CPDistance": 5000, "CPField": "TimeChk_35km", "CPAccumulate": 29220, "unixTOD": 1734224367.35, "unixtime": 1734224367.35, "chip_time": "8944.500", "time": "08:59:27", "section_total_rank": null, "sTime": "00:21:39", "cumulativeTime": "02:29:05", "raceTime": "02:29:05", "averageRate": "04:15", "speed": 3.85, "rate": 260, "sRate": "04:19"}, "10": {"CPId": "10", "CPName": "40k", "CPDistance": 5000, "CPField": "TimeChk_40km", "CPAccumulate": 34220, "unixTOD": 1734225678.9, "unixtime": 1734225678.9, "chip_time": "10256.050", "time": "09:21:18", "section_total_rank": null, "sTime": "00:21:52", "cumulativeTime": "02:50:57", "raceTime": "02:50:57", "averageRate": "04:16", "speed": 3.81, "rate": 262, "sRate": "04:22"}, "11": {"CPId": "99", "CPName": "FINISH", "CPDistance": 2195, "CPField": "TimeFinish", "CPAccumulate": 36415, "unixTOD": 1734226269.15, "unixtime": 1734226269.15, "chip_time": "10846.300", "time": "09:31:09", "section_total_rank": null, "sTime": "00:09:51", "cumulativeTime": "03:00:47", "raceTime": "03:00:47", "averageRate": "04:17", "speed": 3.72, "rate": 269, "sRate": "04:28"}}, "estimatePosition": "42.195 KM", "estimateDistance": 42195, "estimateComplete": "\u5df2\u62b5\u9054", "totalDistance": 42195, "estimatePercent": 100}}