{"runner_info": {"Bib Number": "008643", "Name": "Chau Tsz Kit", "Event": "MA", "Group": "\u753740-49\u6b72", "Nation": "HK", "Gender": "\u7537", "Gun Time": "03:08:00", "Net Time": "03:07:05"}, "record": {"cp": {"-1": {"CPId": "0", "CPName": "Gun Start", "CPDistance": 0, "CPField": "TimeGun", "CPAccumulate": 0, "unixTOD": 1734215400.4, "unixtime": 1734215400.4, "chip_time": 0, "time": "06:30:00", "section_total_rank": null, "sTime": "--:--:--", "cumulativeTime": "00:00:00", "raceTime": "00:00:00", "averageRate": "--:--", "sRate": "--:--"}, "0": {"CPId": "00", "CPName": "Start", "CPDistance": 0, "CPField": "TimeStart", "CPAccumulate": 0, "unixTOD": 1734215455.15, "unixtime": 1734215455.15, "chip_time": 0, "time": "06:30:55", "section_total_rank": null, "sTime": "--:--:--", "cumulativeTime": "00:00:00", "raceTime": "00:00:00", "averageRate": "--:--", "sRate": "--:--"}, "1": {"CPId": "01", "CPName": "5k", "CPDistance": 5000, "CPField": "TimeChk_05km", "CPAccumulate": 5000, "unixTOD": 1734216741.05, "unixtime": 1734216741.05, "chip_time": "1285.900", "time": "06:52:21", "section_total_rank": null, "sTime": "00:21:26", "cumulativeTime": "00:21:26", "raceTime": "00:21:26", "averageRate": "04:17", "speed": 3.89, "rate": 257, "sRate": "04:17"}, "2": {"CPId": "02", "CPName": "10k", "CPDistance": 5000, "CPField": "TimeChk_10km", "CPAccumulate": 10000, "unixTOD": 1734218030.1, "unixtime": 1734218030.1, "chip_time": "2574.950", "time": "07:13:50", "section_total_rank": null, "sTime": "00:21:30", "cumulativeTime": "00:42:55", "raceTime": "00:42:55", "averageRate": "04:17", "speed": 3.88, "rate": 258, "sRate": "04:17"}, "3": {"CPId": "03", "CPName": "15k", "CPDistance": 5000, "CPField": "TimeChk_15km", "CPAccumulate": 15000, "unixTOD": 1734219298.1, "unixtime": 1734219298.1, "chip_time": "3842.950", "time": "07:34:58", "section_total_rank": null, "sTime": "00:21:08", "cumulativeTime": "01:04:03", "raceTime": "01:04:03", "averageRate": "04:16", "speed": 3.94, "rate": 254, "sRate": "04:13"}, "4": {"CPId": "04", "CPName": "20k", "CPDistance": 5000, "CPField": "TimeChk_20km", "CPAccumulate": 20000, "unixTOD": 1734220578.6, "unixtime": 1734220578.6, "chip_time": "5123.450", "time": "07:56:18", "section_total_rank": null, "sTime": "00:21:21", "cumulativeTime": "01:25:24", "raceTime": "01:25:24", "averageRate": "04:16", "speed": 3.9, "rate": 256, "sRate": "04:16"}, "5": {"CPId": "05", "CPName": "21k", "CPDistance": 1000, "CPField": "TimeSplitM1", "CPAccumulate": 15220, "unixTOD": 1734220862.15, "unixtime": 1734220862.15, "chip_time": "5407.000", "time": "08:01:02", "section_total_rank": null, "sTime": "00:04:44", "cumulativeTime": "01:30:07", "raceTime": "01:30:07", "averageRate": "04:17", "speed": 3.53, "rate": 284, "sRate": "04:43"}, "6": {"CPId": "06", "CPName": "25k", "CPDistance": 4000, "CPField": "TimeChk_25km", "CPAccumulate": 19220, "unixTOD": 1734221906.5, "unixtime": 1734221906.5, "chip_time": "6451.350", "time": "08:18:26", "section_total_rank": null, "sTime": "00:17:25", "cumulativeTime": "01:47:32", "raceTime": "01:47:32", "averageRate": "04:18", "speed": 3.83, "rate": 261, "sRate": "04:21"}, "7": {"CPId": "07", "CPName": "26k", "CPDistance": 1000, "CPField": "TimeSplitM2", "CPAccumulate": 20220, "unixTOD": 1734222393.45, "unixtime": 1734222393.45, "chip_time": "6938.300", "time": "08:26:33", "section_total_rank": null, "sTime": "00:08:07", "cumulativeTime": "01:55:39", "raceTime": "01:55:39", "averageRate": "04:26", "speed": 2.05, "rate": 487, "sRate": "08:06"}, "8": {"CPId": "08", "CPName": "30k", "CPDistance": 4000, "CPField": "TimeChk_30km", "CPAccumulate": 24220, "unixTOD": 1734223263.45, "unixtime": 1734223263.45, "chip_time": "7808.300", "time": "08:41:03", "section_total_rank": null, "sTime": "00:14:30", "cumulativeTime": "02:10:09", "raceTime": "02:10:09", "averageRate": "04:20", "speed": 4.6, "rate": 218, "sRate": "03:37"}, "9": {"CPId": "09", "CPName": "35k", "CPDistance": 5000, "CPField": "TimeChk_35km", "CPAccumulate": 29220, "unixTOD": 1734224637.2, "unixtime": 1734224637.2, "chip_time": "9182.050", "time": "09:03:57", "section_total_rank": null, "sTime": "00:22:54", "cumulativeTime": "02:33:03", "raceTime": "02:33:03", "averageRate": "04:22", "speed": 3.64, "rate": 275, "sRate": "04:34"}, "10": {"CPId": "10", "CPName": "40k", "CPDistance": 5000, "CPField": "TimeChk_40km", "CPAccumulate": 34220, "unixTOD": 1734226037.3, "unixtime": 1734226037.3, "chip_time": "10582.150", "time": "09:27:17", "section_total_rank": null, "sTime": "00:23:21", "cumulativeTime": "02:56:23", "raceTime": "02:56:23", "averageRate": "04:24", "speed": 3.57, "rate": 280, "sRate": "04:40"}, "11": {"CPId": "99", "CPName": "FINISH", "CPDistance": 2195, "CPField": "TimeFinish", "CPAccumulate": 36415, "unixTOD": 1734226680.05, "unixtime": 1734226680.05, "chip_time": "11224.900", "time": "09:38:00", "section_total_rank": null, "sTime": "00:10:43", "cumulativeTime": "03:07:05", "raceTime": "03:07:05", "averageRate": "04:26", "speed": 3.42, "rate": 293, "sRate": "04:52"}}, "estimatePosition": "42.195 KM", "estimateDistance": 42195, "estimateComplete": "\u5df2\u62b5\u9054", "totalDistance": 42195, "estimatePercent": 100}}