{"runner_info": {"Bib Number": "009249", "Name": "\u90ed\u52f3\u8070", "Event": "MA", "Group": "\u753750-59\u6b72", "Nation": "TPE", "Gender": "\u7537", "Gun Time": "03:09:12", "Net Time": "03:07:01"}, "record": {"cp": {"-1": {"CPId": "0", "CPName": "Gun Start", "CPDistance": 0, "CPField": "TimeGun", "CPAccumulate": 0, "unixTOD": 1734215400.4, "unixtime": 1734215400.4, "chip_time": 0, "time": "06:30:00", "section_total_rank": null, "sTime": "--:--:--", "cumulativeTime": "00:00:00", "raceTime": "00:00:00", "averageRate": "--:--", "sRate": "--:--"}, "0": {"CPId": "00", "CPName": "Start", "CPDistance": 0, "CPField": "TimeStart", "CPAccumulate": 0, "unixTOD": 1734215531.95, "unixtime": 1734215531.95, "chip_time": 0, "time": "06:32:11", "section_total_rank": null, "sTime": "--:--:--", "cumulativeTime": "00:00:00", "raceTime": "00:00:00", "averageRate": "--:--", "sRate": "--:--"}, "1": {"CPId": "01", "CPName": "5k", "CPDistance": 5000, "CPField": "TimeChk_05km", "CPAccumulate": 5000, "unixTOD": 1734216915.2, "unixtime": 1734216915.2, "chip_time": "1383.250", "time": "06:55:15", "section_total_rank": null, "sTime": "00:23:04", "cumulativeTime": "00:23:04", "raceTime": "00:23:04", "averageRate": "04:36", "speed": 3.61, "rate": 277, "sRate": "04:36"}, "2": {"CPId": "02", "CPName": "10k", "CPDistance": 5000, "CPField": "TimeChk_10km", "CPAccumulate": 10000, "unixTOD": 1734218255.45, "unixtime": 1734218255.45, "chip_time": "2723.500", "time": "07:17:35", "section_total_rank": null, "sTime": "00:22:21", "cumulativeTime": "00:45:24", "raceTime": "00:45:24", "averageRate": "04:32", "speed": 3.73, "rate": 268, "sRate": "04:28"}, "3": {"CPId": "03", "CPName": "15k", "CPDistance": 5000, "CPField": "TimeChk_15km", "CPAccumulate": 15000, "unixTOD": 1734219515.25, "unixtime": 1734219515.25, "chip_time": "3983.300", "time": "07:38:35", "section_total_rank": null, "sTime": "00:21:00", "cumulativeTime": "01:06:24", "raceTime": "01:06:24", "averageRate": "04:25", "speed": 3.97, "rate": 252, "sRate": "04:11"}, "4": {"CPId": "04", "CPName": "20k", "CPDistance": 5000, "CPField": "TimeChk_20km", "CPAccumulate": 20000, "unixTOD": 1734220807.05, "unixtime": 1734220807.05, "chip_time": "5275.100", "time": "08:00:07", "section_total_rank": null, "sTime": "00:21:32", "cumulativeTime": "01:27:56", "raceTime": "01:27:56", "averageRate": "04:23", "speed": 3.87, "rate": 258, "sRate": "04:18"}, "5": {"CPId": "05", "CPName": "21k", "CPDistance": 1000, "CPField": "TimeSplitM1", "CPAccumulate": 15220, "unixTOD": 1734221100.35, "unixtime": 1734221100.35, "chip_time": "5568.400", "time": "08:05:00", "section_total_rank": null, "sTime": "00:04:54", "cumulativeTime": "01:32:49", "raceTime": "01:32:49", "averageRate": "04:25", "speed": 3.41, "rate": 293, "sRate": "04:53"}, "6": {"CPId": "06", "CPName": "25k", "CPDistance": 4000, "CPField": "TimeChk_25km", "CPAccumulate": 19220, "unixTOD": 1734222154.85, "unixtime": 1734222154.85, "chip_time": "6622.900", "time": "08:22:34", "section_total_rank": null, "sTime": "00:17:35", "cumulativeTime": "01:50:23", "raceTime": "01:50:23", "averageRate": "04:24", "speed": 3.79, "rate": 264, "sRate": "04:23"}, "7": {"CPId": "07", "CPName": "26k", "CPDistance": 1000, "CPField": "TimeSplitM2", "CPAccumulate": 20220, "unixTOD": 1734222638.55, "unixtime": 1734222638.55, "chip_time": "7106.600", "time": "08:30:38", "section_total_rank": null, "sTime": "00:08:04", "cumulativeTime": "01:58:27", "raceTime": "01:58:27", "averageRate": "04:33", "speed": 2.07, "rate": 484, "sRate": "08:03"}, "8": {"CPId": "08", "CPName": "30k", "CPDistance": 4000, "CPField": "TimeChk_30km", "CPAccumulate": 24220, "unixTOD": 1734223486.1, "unixtime": 1734223486.1, "chip_time": "7954.150", "time": "08:44:46", "section_total_rank": null, "sTime": "00:14:08", "cumulativeTime": "02:12:35", "raceTime": "02:12:35", "averageRate": "04:25", "speed": 4.72, "rate": 212, "sRate": "03:31"}, "9": {"CPId": "09", "CPName": "35k", "CPDistance": 5000, "CPField": "TimeChk_35km", "CPAccumulate": 29220, "unixTOD": 1734224794.15, "unixtime": 1734224794.15, "chip_time": "9262.200", "time": "09:06:34", "section_total_rank": null, "sTime": "00:21:49", "cumulativeTime": "02:34:23", "raceTime": "02:34:23", "averageRate": "04:24", "speed": 3.82, "rate": 262, "sRate": "04:21"}, "10": {"CPId": "10", "CPName": "40k", "CPDistance": 5000, "CPField": "TimeChk_40km", "CPAccumulate": 34220, "unixTOD": 1734226139.75, "unixtime": 1734226139.75, "chip_time": "10607.800", "time": "09:28:59", "section_total_rank": null, "sTime": "00:22:26", "cumulativeTime": "02:56:48", "raceTime": "02:56:48", "averageRate": "04:25", "speed": 3.72, "rate": 269, "sRate": "04:29"}, "11": {"CPId": "99", "CPName": "FINISH", "CPDistance": 2195, "CPField": "TimeFinish", "CPAccumulate": 36415, "unixTOD": 1734226752.2, "unixtime": 1734226752.2, "chip_time": "11220.250", "time": "09:39:12", "section_total_rank": null, "sTime": "00:10:13", "cumulativeTime": "03:07:01", "raceTime": "03:07:01", "averageRate": "04:25", "speed": 3.58, "rate": 279, "sRate": "04:39"}}, "estimatePosition": "42.195 KM", "estimateDistance": 42195, "estimateComplete": "\u5df2\u62b5\u9054", "totalDistance": 42195, "estimatePercent": 100}}