{"runner_info": {"Bib Number": "009575", "Name": "\u6797\u6d69\u6b0a", "Event": "MA", "Group": "\u753740-49\u6b72", "Nation": "HK", "Gender": "\u7537", "Gun Time": "03:37:26", "Net Time": "03:35:48"}, "record": {"cp": {"-1": {"CPId": "0", "CPName": "Gun Start", "CPDistance": 0, "CPField": "TimeGun", "CPAccumulate": 0, "unixTOD": 1734215400.4, "unixtime": 1734215400.4, "chip_time": 0, "time": "06:30:00", "section_total_rank": null, "sTime": "--:--:--", "cumulativeTime": "00:00:00", "raceTime": "00:00:00", "averageRate": "--:--", "sRate": "--:--"}, "0": {"CPId": "00", "CPName": "Start", "CPDistance": 0, "CPField": "TimeStart", "CPAccumulate": 0, "unixTOD": 1734215498.25, "unixtime": 1734215498.25, "chip_time": 0, "time": "06:31:38", "section_total_rank": null, "sTime": "--:--:--", "cumulativeTime": "00:00:00", "raceTime": "00:00:00", "averageRate": "--:--", "sRate": "--:--"}, "1": {"CPId": "01", "CPName": "5k", "CPDistance": 5000, "CPField": "TimeChk_05km", "CPAccumulate": 5000, "unixTOD": 1734216984.45, "unixtime": 1734216984.45, "chip_time": "1486.200", "time": "06:56:24", "section_total_rank": null, "sTime": "00:24:47", "cumulativeTime": "00:24:47", "raceTime": "00:24:47", "averageRate": "04:57", "speed": 3.36, "rate": 297, "sRate": "04:57"}, "2": {"CPId": "02", "CPName": "10k", "CPDistance": 5000, "CPField": "TimeChk_10km", "CPAccumulate": 10000, "unixTOD": 1734218464.6, "unixtime": 1734218464.6, "chip_time": "2966.350", "time": "07:21:04", "section_total_rank": null, "sTime": "00:24:41", "cumulativeTime": "00:49:27", "raceTime": "00:49:27", "averageRate": "04:56", "speed": 3.38, "rate": 296, "sRate": "04:56"}, "3": {"CPId": "03", "CPName": "15k", "CPDistance": 5000, "CPField": "TimeChk_15km", "CPAccumulate": 15000, "unixTOD": 1734219973.9, "unixtime": 1734219973.9, "chip_time": "4475.650", "time": "07:46:13", "section_total_rank": null, "sTime": "00:25:10", "cumulativeTime": "01:14:36", "raceTime": "01:14:36", "averageRate": "04:58", "speed": 3.31, "rate": 302, "sRate": "05:01"}, "4": {"CPId": "04", "CPName": "20k", "CPDistance": 5000, "CPField": "TimeChk_20km", "CPAccumulate": 20000, "unixTOD": 1734221467.45, "unixtime": 1734221467.45, "chip_time": "5969.200", "time": "08:11:07", "section_total_rank": null, "sTime": "00:24:54", "cumulativeTime": "01:39:30", "raceTime": "01:39:30", "averageRate": "04:58", "speed": 3.35, "rate": 299, "sRate": "04:58"}, "5": {"CPId": "05", "CPName": "21k", "CPDistance": 1000, "CPField": "TimeSplitM1", "CPAccumulate": 15220, "unixTOD": 1734221814.95, "unixtime": 1734221814.95, "chip_time": "6316.700", "time": "08:16:54", "section_total_rank": null, "sTime": "00:05:48", "cumulativeTime": "01:45:17", "raceTime": "01:45:17", "averageRate": "05:00", "speed": 2.88, "rate": 348, "sRate": "05:47"}, "6": {"CPId": "06", "CPName": "25k", "CPDistance": 4000, "CPField": "TimeChk_25km", "CPAccumulate": 19220, "unixTOD": 1734223013.1, "unixtime": 1734223013.1, "chip_time": "7514.850", "time": "08:36:53", "section_total_rank": null, "sTime": "00:19:59", "cumulativeTime": "02:05:15", "raceTime": "02:05:15", "averageRate": "05:00", "speed": 3.34, "rate": 300, "sRate": "04:59"}, "7": {"CPId": "07", "CPName": "26k", "CPDistance": 1000, "CPField": "TimeSplitM2", "CPAccumulate": 20220, "unixTOD": 1734223561.3, "unixtime": 1734223561.3, "chip_time": "8063.050", "time": "08:46:01", "section_total_rank": null, "sTime": "00:09:09", "cumulativeTime": "02:14:24", "raceTime": "02:14:24", "averageRate": "05:10", "speed": 1.82, "rate": 548, "sRate": "09:08"}, "8": {"CPId": "08", "CPName": "30k", "CPDistance": 4000, "CPField": "TimeChk_30km", "CPAccumulate": 24220, "unixTOD": 1734224540.25, "unixtime": 1734224540.25, "chip_time": "9042.000", "time": "09:02:20", "section_total_rank": null, "sTime": "00:16:19", "cumulativeTime": "02:30:42", "raceTime": "02:30:42", "averageRate": "05:01", "speed": 4.09, "rate": 245, "sRate": "04:04"}, "9": {"CPId": "09", "CPName": "35k", "CPDistance": 5000, "CPField": "TimeChk_35km", "CPAccumulate": 29220, "unixTOD": 1734226052.8, "unixtime": 1734226052.8, "chip_time": "10554.550", "time": "09:27:32", "section_total_rank": null, "sTime": "00:25:13", "cumulativeTime": "02:55:55", "raceTime": "02:55:55", "averageRate": "05:01", "speed": 3.31, "rate": 303, "sRate": "05:02"}, "10": {"CPId": "10", "CPName": "40k", "CPDistance": 5000, "CPField": "TimeChk_40km", "CPAccumulate": 34220, "unixTOD": 1734227631.05, "unixtime": 1734227631.05, "chip_time": "12132.800", "time": "09:53:51", "section_total_rank": null, "sTime": "00:26:19", "cumulativeTime": "03:22:13", "raceTime": "03:22:13", "averageRate": "05:03", "speed": 3.17, "rate": 316, "sRate": "05:15"}, "11": {"CPId": "99", "CPName": "FINISH", "CPDistance": 2195, "CPField": "TimeFinish", "CPAccumulate": 36415, "unixTOD": 1734228445.6, "unixtime": 1734228445.6, "chip_time": "12947.350", "time": "10:07:25", "section_total_rank": null, "sTime": "00:13:35", "cumulativeTime": "03:35:48", "raceTime": "03:35:48", "averageRate": "05:06", "speed": 2.69, "rate": 371, "sRate": "06:11"}}, "estimatePosition": "42.195 KM", "estimateDistance": 42195, "estimateComplete": "\u5df2\u62b5\u9054", "totalDistance": 42195, "estimatePercent": 100}}