{"runner_info": {"Bib Number": "012536", "Name": "\u53e4\u6b23\u5a55", "Event": "MA", "Group": "\u597340-49\u6b72", "Nation": "TPE", "Gender": "\u5973", "Gun Time": "04:11:57", "Net Time": "04:10:45"}, "record": {"cp": {"-1": {"CPId": "0", "CPName": "Gun Start", "CPDistance": 0, "CPField": "TimeGun", "CPAccumulate": 0, "unixTOD": 1734215400.4, "unixtime": 1734215400.4, "chip_time": 0, "time": "06:30:00", "section_total_rank": null, "sTime": "--:--:--", "cumulativeTime": "00:00:00", "raceTime": "00:00:00", "averageRate": "--:--", "sRate": "--:--"}, "0": {"CPId": "00", "CPName": "Start", "CPDistance": 0, "CPField": "TimeStart", "CPAccumulate": 0, "unixTOD": 1734215473.05, "unixtime": 1734215473.05, "chip_time": 0, "time": "06:31:13", "section_total_rank": null, "sTime": "--:--:--", "cumulativeTime": "00:00:00", "raceTime": "00:00:00", "averageRate": "--:--", "sRate": "--:--"}, "1": {"CPId": "01", "CPName": "5k", "CPDistance": 5000, "CPField": "TimeChk_05km", "CPAccumulate": 5000, "unixTOD": 1734217077.95, "unixtime": 1734217077.95, "chip_time": "1604.900", "time": "06:57:57", "section_total_rank": null, "sTime": "00:26:45", "cumulativeTime": "00:26:45", "raceTime": "00:26:45", "averageRate": "05:20", "speed": 3.12, "rate": 321, "sRate": "05:20"}, "2": {"CPId": "02", "CPName": "10k", "CPDistance": 5000, "CPField": "TimeChk_10km", "CPAccumulate": 10000, "unixTOD": 1734218715.35, "unixtime": 1734218715.35, "chip_time": "3242.300", "time": "07:25:15", "section_total_rank": null, "sTime": "00:27:18", "cumulativeTime": "00:54:03", "raceTime": "00:54:03", "averageRate": "05:24", "speed": 3.05, "rate": 327, "sRate": "05:27"}, "3": {"CPId": "03", "CPName": "15k", "CPDistance": 5000, "CPField": "TimeChk_15km", "CPAccumulate": 15000, "unixTOD": 1734220383.2, "unixtime": 1734220383.2, "chip_time": "4910.150", "time": "07:53:03", "section_total_rank": null, "sTime": "00:27:48", "cumulativeTime": "01:21:51", "raceTime": "01:21:51", "averageRate": "05:27", "speed": 3, "rate": 334, "sRate": "05:33"}, "4": {"CPId": "04", "CPName": "20k", "CPDistance": 5000, "CPField": "TimeChk_20km", "CPAccumulate": 20000, "unixTOD": 1734222210.85, "unixtime": 1734222210.85, "chip_time": "6737.800", "time": "08:23:30", "section_total_rank": null, "sTime": "00:30:28", "cumulativeTime": "01:52:18", "raceTime": "01:52:18", "averageRate": "05:36", "speed": 2.74, "rate": 366, "sRate": "06:05"}, "5": {"CPId": "05", "CPName": "21k", "CPDistance": 1000, "CPField": "TimeSplitM1", "CPAccumulate": 15220, "unixTOD": 1734222667.55, "unixtime": 1734222667.55, "chip_time": "7194.500", "time": "08:31:07", "section_total_rank": null, "sTime": "00:07:37", "cumulativeTime": "01:59:55", "raceTime": "01:59:55", "averageRate": "05:42", "speed": 2.19, "rate": 457, "sRate": "07:36"}, "6": {"CPId": "06", "CPName": "25k", "CPDistance": 4000, "CPField": "TimeChk_25km", "CPAccumulate": 19220, "unixTOD": 1734224114.8, "unixtime": 1734224114.8, "chip_time": "8641.750", "time": "08:55:14", "section_total_rank": null, "sTime": "00:24:08", "cumulativeTime": "02:24:02", "raceTime": "02:24:02", "averageRate": "05:45", "speed": 2.76, "rate": 362, "sRate": "06:01"}, "7": {"CPId": "07", "CPName": "26k", "CPDistance": 1000, "CPField": "TimeSplitM2", "CPAccumulate": 20220, "unixTOD": 1734224808.15, "unixtime": 1734224808.15, "chip_time": "9335.100", "time": "09:06:48", "section_total_rank": null, "sTime": "00:11:34", "cumulativeTime": "02:35:36", "raceTime": "02:35:36", "averageRate": "05:59", "speed": 1.44, "rate": 693, "sRate": "11:33"}, "8": {"CPId": "08", "CPName": "30k", "CPDistance": 4000, "CPField": "TimeChk_30km", "CPAccumulate": 24220, "unixTOD": 1734226011.9, "unixtime": 1734226011.9, "chip_time": "10538.850", "time": "09:26:51", "section_total_rank": null, "sTime": "00:20:04", "cumulativeTime": "02:55:39", "raceTime": "02:55:39", "averageRate": "05:51", "speed": 3.32, "rate": 301, "sRate": "05:00"}, "9": {"CPId": "09", "CPName": "35k", "CPDistance": 5000, "CPField": "TimeChk_35km", "CPAccumulate": 29220, "unixTOD": 1734227916.65, "unixtime": 1734227916.65, "chip_time": "12443.600", "time": "09:58:36", "section_total_rank": null, "sTime": "00:31:45", "cumulativeTime": "03:27:24", "raceTime": "03:27:24", "averageRate": "05:55", "speed": 2.63, "rate": 381, "sRate": "06:20"}, "10": {"CPId": "10", "CPName": "40k", "CPDistance": 5000, "CPField": "TimeChk_40km", "CPAccumulate": 34220, "unixTOD": 1734229708.05, "unixtime": 1734229708.05, "chip_time": "14235.000", "time": "10:28:28", "section_total_rank": null, "sTime": "00:29:52", "cumulativeTime": "03:57:15", "raceTime": "03:57:15", "averageRate": "05:55", "speed": 2.79, "rate": 358, "sRate": "05:58"}, "11": {"CPId": "99", "CPName": "FINISH", "CPDistance": 2195, "CPField": "TimeFinish", "CPAccumulate": 36415, "unixTOD": 1734230517.35, "unixtime": 1734230517.35, "chip_time": "15044.300", "time": "10:41:57", "section_total_rank": null, "sTime": "00:13:30", "cumulativeTime": "04:10:45", "raceTime": "04:10:45", "averageRate": "05:56", "speed": 2.71, "rate": 369, "sRate": "06:08"}}, "estimatePosition": "42.195 KM", "estimateDistance": 42195, "estimateComplete": "\u5df2\u62b5\u9054", "totalDistance": 42195, "estimatePercent": 100}}